pysafepass/__init__.py
pysafepass/__main__.py
pysafepass/db.py
pysafepass/encrypt.py
pysafepass/gui.py
pysafepass/hash.py
pysafepass/paths.py
pysafepass/user.py
pysafepass/.images/safepass.png
pysafepass/.images/safepass_win.ico
pysafepass/UI/CreateAccount.ui
pysafepass/UI/PasswordsTable.ui
pysafepass/UI/SaveInfo.ui
pysafepass/UI/login.ui
pysafepass/db/passwords.db
pysafepass/db/users.db
PySafePass-1.0.4.dist-info/LICENSE.md
PySafePass-1.0.4.dist-info/METADATA
PySafePass-1.0.4.dist-info/WHEEL
PySafePass-1.0.4.dist-info/top_level.txt
PySafePass-1.0.4.dist-info/RECORD
