Metadata-Version: 2.1
Name: PySafePass
Version: 1.0.4
Summary: SafePass is an Open Source Password Manager. SafePass is released as PySafePass on PyPi.
Home-page: UNKNOWN
License: MIT License
Platform: UNKNOWN
Requires-Dist: pyqt5
Requires-Dist: pyperclip
Requires-Dist: cryptography
